<?xml version="1.0" encoding="utf-8"?><HelpTOCNode Title="FlightCtrlState Fields" Url="html/Fields_T_FlightCtrlState.htm"><HelpTOCNode Title="custom_axes Field" Url="html/F_FlightCtrlState_custom_axes.htm" /><HelpTOCNode Title="gearDown Field" Url="html/F_FlightCtrlState_gearDown.htm" /><HelpTOCNode Title="gearUp Field" Url="html/F_FlightCtrlState_gearUp.htm" /><HelpTOCNode Title="headlight Field" Url="html/F_FlightCtrlState_headlight.htm" /><HelpTOCNode Title="killRot Field" Url="html/F_FlightCtrlState_killRot.htm" /><HelpTOCNode Title="mainThrottle Field" Url="html/F_FlightCtrlState_mainThrottle.htm" /><HelpTOCNode Title="pitch Field" Url="html/F_FlightCtrlState_pitch.htm" /><HelpTOCNode Title="pitchTrim Field" Url="html/F_FlightCtrlState_pitchTrim.htm" /><HelpTOCNode Title="roll Field" Url="html/F_FlightCtrlState_roll.htm" /><HelpTOCNode Title="rollTrim Field" Url="html/F_FlightCtrlState_rollTrim.htm" /><HelpTOCNode Title="wheelSteer Field" Url="html/F_FlightCtrlState_wheelSteer.htm" /><HelpTOCNode Title="wheelSteerTrim Field" Url="html/F_FlightCtrlState_wheelSteerTrim.htm" /><HelpTOCNode Title="wheelThrottle Field" Url="html/F_FlightCtrlState_wheelThrottle.htm" /><HelpTOCNode Title="wheelThrottleTrim Field" Url="html/F_FlightCtrlState_wheelThrottleTrim.htm" /><HelpTOCNode Title="X Field" Url="html/F_FlightCtrlState_X.htm" /><HelpTOCNode Title="Y Field" Url="html/F_FlightCtrlState_Y.htm" /><HelpTOCNode Title="yaw Field" Url="html/F_FlightCtrlState_yaw.htm" /><HelpTOCNode Title="yawTrim Field" Url="html/F_FlightCtrlState_yawTrim.htm" /><HelpTOCNode Title="Z Field" Url="html/F_FlightCtrlState_Z.htm" /></HelpTOCNode>