<?xml version="1.0" encoding="utf-8"?><HelpTOCNode Title="ShipTemplate Fields" Url="html/Fields_T_ShipTemplate.htm"><HelpTOCNode Title="config Field" Url="html/F_ShipTemplate_config.htm" /><HelpTOCNode Title="dryCost Field" Url="html/F_ShipTemplate_dryCost.htm" /><HelpTOCNode Title="duplicatedParts Field" Url="html/F_ShipTemplate_duplicatedParts.htm" /><HelpTOCNode Title="filename Field" Url="html/F_ShipTemplate_filename.htm" /><HelpTOCNode Title="fuelCost Field" Url="html/F_ShipTemplate_fuelCost.htm" /><HelpTOCNode Title="isControllable Field" Url="html/F_ShipTemplate_isControllable.htm" /><HelpTOCNode Title="partCount Field" Url="html/F_ShipTemplate_partCount.htm" /><HelpTOCNode Title="rootPartNode Field" Url="html/F_ShipTemplate_rootPartNode.htm" /><HelpTOCNode Title="shipDescription Field" Url="html/F_ShipTemplate_shipDescription.htm" /><HelpTOCNode Title="shipName Field" Url="html/F_ShipTemplate_shipName.htm" /><HelpTOCNode Title="shipPartsExperimental Field" Url="html/F_ShipTemplate_shipPartsExperimental.htm" /><HelpTOCNode Title="shipPartsUnlocked Field" Url="html/F_ShipTemplate_shipPartsUnlocked.htm" /><HelpTOCNode Title="shipSize Field" Url="html/F_ShipTemplate_shipSize.htm" /><HelpTOCNode Title="shipType Field" Url="html/F_ShipTemplate_shipType.htm" /><HelpTOCNode Title="stageCount Field" Url="html/F_ShipTemplate_stageCount.htm" /><HelpTOCNode Title="totalCost Field" Url="html/F_ShipTemplate_totalCost.htm" /><HelpTOCNode Title="totalMass Field" Url="html/F_ShipTemplate_totalMass.htm" /></HelpTOCNode>