<?xml version="1.0" encoding="utf-8"?><HelpTOCNode Title="MoveUpdate Fields" Url="html/Fields_T_iT_MoveUpdate.htm"><HelpTOCNode Title="axis Field" Url="html/F_iT_MoveUpdate_axis.htm" /><HelpTOCNode Title="islocal Field" Url="html/F_iT_MoveUpdate_islocal.htm" /><HelpTOCNode Title="looktarget Field" Url="html/F_iT_MoveUpdate_looktarget.htm" /><HelpTOCNode Title="looktime Field" Url="html/F_iT_MoveUpdate_looktime.htm" /><HelpTOCNode Title="orienttopath Field" Url="html/F_iT_MoveUpdate_orienttopath.htm" /><HelpTOCNode Title="position Field" Url="html/F_iT_MoveUpdate_position.htm" /><HelpTOCNode Title="time Field" Url="html/F_iT_MoveUpdate_time.htm" /><HelpTOCNode Title="x Field" Url="html/F_iT_MoveUpdate_x.htm" /><HelpTOCNode Title="y Field" Url="html/F_iT_MoveUpdate_y.htm" /><HelpTOCNode Title="z Field" Url="html/F_iT_MoveUpdate_z.htm" /></HelpTOCNode>