<?xml version="1.0" encoding="utf-8"?><HelpTOCNode Title="VesselModule Methods" Url="html/Methods_T_VesselModule.htm"><HelpTOCNode Title="GetActivation Method " Url="html/M_VesselModule_GetActivation.htm" /><HelpTOCNode Title="GetOrder Method " Url="html/M_VesselModule_GetOrder.htm" /><HelpTOCNode Title="Load Method " Url="html/M_VesselModule_Load.htm" /><HelpTOCNode Title="OnGoOffRails Method " Url="html/M_VesselModule_OnGoOffRails.htm" /><HelpTOCNode Title="OnGoOnRails Method " Url="html/M_VesselModule_OnGoOnRails.htm" /><HelpTOCNode Title="OnLoadVessel Method " Url="html/M_VesselModule_OnLoadVessel.htm" /><HelpTOCNode Title="OnUnloadVessel Method " Url="html/M_VesselModule_OnUnloadVessel.htm" /><HelpTOCNode Title="Save Method " Url="html/M_VesselModule_Save.htm" /><HelpTOCNode Title="ShouldBeActive Method " Url="html/M_VesselModule_ShouldBeActive.htm" /></HelpTOCNode>