<?xml version="1.0" encoding="utf-8"?><HelpTOCNode Title="UIList Methods" Url="html/Methods_T_KSP_UI_UIList.htm"><HelpTOCNode Title="AddItem Method " Url="html/M_KSP_UI_UIList_AddItem.htm" /><HelpTOCNode Title="Clear Method " Url="html/M_KSP_UI_UIList_Clear.htm" /><HelpTOCNode Title="ClearUI Method " Url="html/M_KSP_UI_UIList_ClearUI.htm" /><HelpTOCNode Title="Contains Method " Url="html/M_KSP_UI_UIList_Contains.htm" /><HelpTOCNode Title="GetDropItemIndex Method " Url="html/M_KSP_UI_UIList_GetDropItemIndex.htm" /><HelpTOCNode Title="GetEnumerator Method " Url="html/M_KSP_UI_UIList_GetEnumerator.htm" /><HelpTOCNode Title="GetIndex Method " Url="html/M_KSP_UI_UIList_GetIndex.htm" /><HelpTOCNode Title="GetUilistItemAt Method " Url="html/M_KSP_UI_UIList_GetUilistItemAt.htm" /><HelpTOCNode Title="GetUiListItems Method " Url="html/M_KSP_UI_UIList_GetUiListItems.htm" /><HelpTOCNode Title="InsertItem Method " Url="html/M_KSP_UI_UIList_InsertItem.htm" /><HelpTOCNode Title="Refresh Method " Url="html/M_KSP_UI_UIList_Refresh.htm" /><HelpTOCNode Title="RemoveItem Method " Url="html/Overload_KSP_UI_UIList_RemoveItem.htm" HasChildren="true" /><HelpTOCNode Title="RemoveItemAndMove Method " Url="html/M_KSP_UI_UIList_RemoveItemAndMove.htm" /><HelpTOCNode Title="SetActive Method " Url="html/M_KSP_UI_UIList_SetActive.htm" /><HelpTOCNode Title="SetAnchor Method " Url="html/M_KSP_UI_UIList_SetAnchor.htm" /><HelpTOCNode Title="SwapItems Method " Url="html/M_KSP_UI_UIList_SwapItems.htm" /></HelpTOCNode>