<?xml version="1.0" encoding="utf-8"?><HelpTOCNode Title="XButton Methods" Url="html/Methods_T_XButton.htm"><HelpTOCNode Title="Create Method " Url="html/M_XButton_Create.htm" /><HelpTOCNode Title="OnDeselect Method " Url="html/M_XButton_OnDeselect.htm" /><HelpTOCNode Title="OnMove Method " Url="html/M_XButton_OnMove.htm" /><HelpTOCNode Title="OnPointerDown Method " Url="html/M_XButton_OnPointerDown.htm" /><HelpTOCNode Title="OnPointerEnter Method " Url="html/M_XButton_OnPointerEnter.htm" /><HelpTOCNode Title="OnPointerExit Method " Url="html/M_XButton_OnPointerExit.htm" /><HelpTOCNode Title="OnPointerUp Method " Url="html/M_XButton_OnPointerUp.htm" /><HelpTOCNode Title="OnSelect Method " Url="html/M_XButton_OnSelect.htm" /><HelpTOCNode Title="Terminate Method " Url="html/M_XButton_Terminate.htm" /></HelpTOCNode>