<?xml version="1.0" encoding="utf-8"?><HelpTOCNode Title="Blit Method " Url="html/Overload_UnityEngine_Graphics_Blit.htm"><HelpTOCNode Title="Blit Method (Texture, Material)" Url="html/M_UnityEngine_Graphics_Blit.htm" /><HelpTOCNode Title="Blit Method (Texture, RenderTexture)" Url="html/M_UnityEngine_Graphics_Blit_3.htm" /><HelpTOCNode Title="Blit Method (Texture, Material, Int32)" Url="html/M_UnityEngine_Graphics_Blit_1.htm" /><HelpTOCNode Title="Blit Method (Texture, RenderTexture, Material)" Url="html/M_UnityEngine_Graphics_Blit_5.htm" /><HelpTOCNode Title="Blit Method (Texture, Material, Int32, Int32)" Url="html/M_UnityEngine_Graphics_Blit_2.htm" /><HelpTOCNode Title="Blit Method (Texture, RenderTexture, Int32, Int32)" Url="html/M_UnityEngine_Graphics_Blit_4.htm" /><HelpTOCNode Title="Blit Method (Texture, RenderTexture, Material, Int32)" Url="html/M_UnityEngine_Graphics_Blit_6.htm" /><HelpTOCNode Title="Blit Method (Texture, RenderTexture, Vector2, Vector2)" Url="html/M_UnityEngine_Graphics_Blit_8.htm" /><HelpTOCNode Title="Blit Method (Texture, RenderTexture, Material, Int32, Int32)" Url="html/M_UnityEngine_Graphics_Blit_7.htm" /><HelpTOCNode Title="Blit Method (Texture, RenderTexture, Vector2, Vector2, Int32, Int32)" Url="html/M_UnityEngine_Graphics_Blit_9.htm" /></HelpTOCNode>